{
  "db_name": "PostgreSQL",
  "query": "SELECT * FROM pentest_engagements \n               WHERE engagement_type = 'third_party_audit' OR follow_up_scheduled_at IS NOT NULL\n               ORDER BY follow_up_scheduled_at",
  "describe": {
    "columns": [
      {
        "ordinal": 0,
        "name": "id",
        "type_info": "Uuid"
      },
      {
        "ordinal": 1,
        "name": "title",
        "type_info": "Varchar"
      },
      {
        "ordinal": 2,
        "name": "engagement_type",
        "type_info": "Varchar"
      },
      {
        "ordinal": 3,
        "name": "audit_type",
        "type_info": {
          "Custom": {
            "name": "third_party_audit_type",
            "kind": {
              "Enum": [
                "white_box",
                "grey_box",
                "black_box",
                "combined"
              ]
            }
          }
        }
      },
      {
        "ordinal": 4,
        "name": "vendor",
        "type_info": "Jsonb"
      },
      {
        "ordinal": 5,
        "name": "scope",
        "type_info": "Jsonb"
      },
      {
        "ordinal": 6,
        "name": "out_of_scope",
        "type_info": "Jsonb"
      },
      {
        "ordinal": 7,
        "name": "testing_team",
        "type_info": "Jsonb"
      },
      {
        "ordinal": 8,
        "name": "status",
        "type_info": {
          "Custom": {
            "name": "pentest_engagement_status",
            "kind": {
              "Enum": [
                "planned",
                "active",
                "completed",
                "cancelled"
              ]
            }
          }
        }
      },
      {
        "ordinal": 9,
        "name": "completion_status",
        "type_info": {
          "Custom": {
            "name": "third_party_completion_status",
            "kind": {
              "Enum": [
                "pending",
                "partial",
                "complete",
                "failed"
              ]
            }
          }
        }
      },
      {
        "ordinal": 10,
        "name": "follow_up_scheduled_at",
        "type_info": "Timestamptz"
      },
      {
        "ordinal": 11,
        "name": "final_report_url",
        "type_info": "Text"
      },
      {
        "ordinal": 12,
        "name": "scheduled_start",
        "type_info": "Timestamptz"
      },
      {
        "ordinal": 13,
        "name": "scheduled_end",
        "type_info": "Timestamptz"
      },
      {
        "ordinal": 14,
        "name": "actual_start",
        "type_info": "Timestamptz"
      },
      {
        "ordinal": 15,
        "name": "actual_end",
        "type_info": "Timestamptz"
      },
      {
        "ordinal": 16,
        "name": "created_by",
        "type_info": "Uuid"
      },
      {
        "ordinal": 17,
        "name": "created_at",
        "type_info": "Timestamptz"
      },
      {
        "ordinal": 18,
        "name": "updated_at",
        "type_info": "Timestamptz"
      }
    ],
    "parameters": {
      "Left": []
    },
    "nullable": [
      false,
      false,
      false,
      true,
      true,
      false,
      false,
      false,
      false,
      true,
      true,
      true,
      true,
      true,
      true,
      true,
      true,
      true,
      true
    ]
  },
  "hash": "92e157500291bc8fb07564a671dde86c7f28934407954883f0f57adbd75c32c6"
}
