{
  "db_name": "PostgreSQL",
  "query": "SELECT * FROM partner_credentials WHERE certificate_fingerprint = $1 AND revoked_at IS NULL",
  "describe": {
    "columns": [
      {
        "ordinal": 0,
        "name": "id",
        "type_info": "Uuid"
      },
      {
        "ordinal": 1,
        "name": "partner_id",
        "type_info": "Uuid"
      },
      {
        "ordinal": 2,
        "name": "credential_type",
        "type_info": "Text"
      },
      {
        "ordinal": 3,
        "name": "client_id",
        "type_info": "Text"
      },
      {
        "ordinal": 4,
        "name": "client_secret_hash",
        "type_info": "Text"
      },
      {
        "ordinal": 5,
        "name": "certificate_fingerprint",
        "type_info": "Text"
      },
      {
        "ordinal": 6,
        "name": "api_key_hash",
        "type_info": "Text"
      },
      {
        "ordinal": 7,
        "name": "api_key_prefix",
        "type_info": "Text"
      },
      {
        "ordinal": 8,
        "name": "scopes",
        "type_info": "TextArray"
      },
      {
        "ordinal": 9,
        "name": "environment",
        "type_info": "Text"
      },
      {
        "ordinal": 10,
        "name": "expires_at",
        "type_info": "Timestamptz"
      },
      {
        "ordinal": 11,
        "name": "revoked_at",
        "type_info": "Timestamptz"
      },
      {
        "ordinal": 12,
        "name": "created_at",
        "type_info": "Timestamptz"
      }
    ],
    "parameters": {
      "Left": [
        "Text"
      ]
    },
    "nullable": [
      false,
      false,
      false,
      true,
      true,
      true,
      true,
      true,
      false,
      false,
      true,
      true,
      false
    ]
  },
  "hash": "9ffd07e5b7143e8cdf308adb1407cf0a8e0b7c4f8fe5b0ee1c4e3d9fc99016fe"
}
