{
  "db_name": "PostgreSQL",
  "query": "\n            INSERT INTO consumer_endpoint_usage (\n                id, consumer_id, endpoint_path, http_method, snapshot_period,\n                period_start, period_end, request_count, success_count,\n                error_count, avg_latency_ms\n            ) VALUES ($1, $2, $3, $4, $5, $6, $7, $8, $9, $10, $11)\n            ON CONFLICT (consumer_id, endpoint_path, http_method, snapshot_period, period_start)\n            DO UPDATE SET\n                request_count = EXCLUDED.request_count,\n                success_count = EXCLUDED.success_count,\n                error_count = EXCLUDED.error_count,\n                avg_latency_ms = EXCLUDED.avg_latency_ms\n            ",
  "describe": {
    "columns": [],
    "parameters": {
      "Left": [
        "Uuid",
        "Text",
        "Text",
        "Text",
        {
          "Custom": {
            "name": "snapshot_period",
            "kind": {
              "Enum": [
                "hourly",
                "daily",
                "weekly",
                "monthly"
              ]
            }
          }
        },
        "Timestamptz",
        "Timestamptz",
        "Int8",
        "Int8",
        "Int8",
        "Int4"
      ]
    },
    "nullable": []
  },
  "hash": "88e9ec1e21e389ece28e5f3d95b673cb0f4d74e3dc5e899b72e4500026b949c8"
}
