{
  "db_name": "PostgreSQL",
  "query": "\n            SELECT \n                position_id, pool_id, strategy_id, shares_owned,\n                asset_a_deposited, asset_b_deposited, initial_share_price,\n                current_share_price, unrealized_yield, impermanent_loss,\n                fee_income_earned, position_opened_at, last_valuation_at, position_status\n            FROM amm_liquidity_positions\n            WHERE position_status = 'active'\n            ",
  "describe": {
    "columns": [
      {
        "ordinal": 0,
        "name": "position_id",
        "type_info": "Uuid"
      },
      {
        "ordinal": 1,
        "name": "pool_id",
        "type_info": "Varchar"
      },
      {
        "ordinal": 2,
        "name": "strategy_id",
        "type_info": "Uuid"
      },
      {
        "ordinal": 3,
        "name": "shares_owned",
        "type_info": "Numeric"
      },
      {
        "ordinal": 4,
        "name": "asset_a_deposited",
        "type_info": "Numeric"
      },
      {
        "ordinal": 5,
        "name": "asset_b_deposited",
        "type_info": "Numeric"
      },
      {
        "ordinal": 6,
        "name": "initial_share_price",
        "type_info": "Numeric"
      },
      {
        "ordinal": 7,
        "name": "current_share_price",
        "type_info": "Numeric"
      },
      {
        "ordinal": 8,
        "name": "unrealized_yield",
        "type_info": "Numeric"
      },
      {
        "ordinal": 9,
        "name": "impermanent_loss",
        "type_info": "Numeric"
      },
      {
        "ordinal": 10,
        "name": "fee_income_earned",
        "type_info": "Numeric"
      },
      {
        "ordinal": 11,
        "name": "position_opened_at",
        "type_info": "Timestamptz"
      },
      {
        "ordinal": 12,
        "name": "last_valuation_at",
        "type_info": "Timestamptz"
      },
      {
        "ordinal": 13,
        "name": "position_status",
        "type_info": "Varchar"
      }
    ],
    "parameters": {
      "Left": []
    },
    "nullable": [
      false,
      false,
      true,
      false,
      false,
      false,
      false,
      false,
      false,
      false,
      false,
      false,
      false,
      false
    ]
  },
  "hash": "866dd3670554cac34bf4f0c4ed1543fb55e462db71f2a62f38b833bd409832cc"
}
